startouch_python_sdk/__init__.py
startouch_python_sdk/libstartouch.so
startouch_python_sdk/startouch_python_sdk.cpython-311-x86_64-linux-gnu.so
startouch_python_sdk/startouchclass.py
startouch_python_sdk/param_csv_gripper/permutationMatrix.csv
startouch_python_sdk/param_csv_gripper/pi_b.csv
startouch_python_sdk/param_csv_gripper/pi_fr.csv
startouch_python_sdk.libs/liborocos-kdl-bd252c63.so.1.4.0
startouch_python_sdk-0.1.1.dist-info/METADATA
startouch_python_sdk-0.1.1.dist-info/WHEEL
startouch_python_sdk-0.1.1.dist-info/entry_points.txt
startouch_python_sdk-0.1.1.dist-info/RECORD
startouch_python_sdk-0.1.1.dist-info/licenses/LICENSE
startouch_python_sdk-0.1.1.dist-info/sboms/auditwheel.cdx.json
