Metadata-Version: 2.2
Name: startouch-python-sdk
Version: 0.1.1
Summary: Precompiled Startouch robot SDK
Author-Email: zhanglijie <zlj15058114997@gmail.com>
Maintainer-Email: zhanglijie <zlj15058114997@gmail.com>
License: MIT
Project-URL: bugs, https://github.com/write-for-bug/startouch_python_sdk/issues
Project-URL: changelog, https://github.com/write-for-bug/startouch_python_sdk/blob/master/changelog.md
Project-URL: homepage, https://github.com/write-for-bug/startouch_python_sdk
Requires-Python: >=3.8
Requires-Dist: typer
Provides-Extra: test
Requires-Dist: coverage; extra == "test"
Requires-Dist: pytest; extra == "test"
Requires-Dist: ruff; extra == "test"
Requires-Dist: ty; extra == "test"
Requires-Dist: ipdb; extra == "test"
